chaosdynatrace/__init__.py
chaosdynatrace/probes.py
chaosdynatrace/events/__init__.py
chaosdynatrace/events/v2/__init__.py
chaosdynatrace/events/v2/control.py
chaosdynatrace/logs/__init__.py
chaosdynatrace/logs/v2/__init__.py
chaosdynatrace/logs/v2/probes.py
chaosdynatrace/metrics/__init__.py
chaosdynatrace/metrics/v2/__init__.py
chaosdynatrace/metrics/v2/probes.py
chaosdynatrace/timeseries/__init__.py
chaosdynatrace/timeseries/v1/__init__.py
chaosdynatrace/timeseries/v1/probes.py
chaostoolkit_dynatrace-0.2.0.dist-info/LICENSE
chaostoolkit_dynatrace-0.2.0.dist-info/METADATA
chaostoolkit_dynatrace-0.2.0.dist-info/WHEEL
chaostoolkit_dynatrace-0.2.0.dist-info/top_level.txt
chaostoolkit_dynatrace-0.2.0.dist-info/RECORD
